{
  "sender": {
    "html_url": "https://github.com/brendandburns", 
    "avatar_url": "https://avatars2.githubusercontent.com/u/5751682?v=4", 
    "gravatar_id": "", 
    "site_admin": false, 
    "login": "brendandburns", 
    "type": "User", 
    "id": 5751682
  }, 
  "repository": {
    "stargazers_count": 26148, 
    "mirror_url": null, 
    "updated_at": "2017-08-22T03:50:19Z", 
    "private": false, 
    "has_wiki": true, 
    "full_name": "kubernetes/kubernetes", 
    "owner": {
      "html_url": "https://github.com/kubernetes", 
      "avatar_url": "https://avatars2.githubusercontent.com/u/13629408?v=4", 
      "gravatar_id": "", 
      "site_admin": false, 
      "login": "kubernetes", 
      "type": "Organization", 
      "id": 13629408
    }, 
    "id": 20580498, 
    "description": "Production-Grade Container Scheduling and Management", 
    "has_pages": false, 
    "open_issues_count": 5327, 
    "has_projects": true, 
    "clone_url": "https://github.com/kubernetes/kubernetes.git", 
    "watchers_count": 26148, 
    "size": 677615, 
    "homepage": "http://kubernetes.io", 
    "fork": false, 
    "html_url": "https://github.com/kubernetes/kubernetes", 
    "forks": 9313, 
    "open_issues": 5327, 
    "git_url": "git://github.com/kubernetes/kubernetes.git", 
    "svn_url": "https://github.com/kubernetes/kubernetes", 
    "has_issues": true, 
    "ssh_url": "git@github.com:kubernetes/kubernetes.git", 
    "has_downloads": true, 
    "watchers": 26148, 
    "name": "kubernetes", 
    "language": "Go", 
    "created_at": "2014-06-06T22:56:04Z", 
    "pushed_at": "2017-08-22T04:27:34Z", 
    "forks_count": 9313, 
    "default_branch": "master"
  }, 
  "review": {
    "body": null, 
    "commit_id": "3257d8d28ba6e4abca8153583869fc9749e809e7", 
    "submitted_at": "2017-08-22T04:43:19Z", 
    "html_url": "https://github.com/kubernetes/kubernetes/pull/51025#pullrequestreview-57666542", 
    "state": "commented", 
    "_links": {
      "html": {
        "href": "https://github.com/kubernetes/kubernetes/pull/51025#pullrequestreview-57666542"
      }, 
      "pull_request": {
        "href": "https://api.github.com/repos/kubernetes/kubernetes/pulls/51025"
      }
    }, 
    "user": {
      "html_url": "https://github.com/brendandburns", 
      "avatar_url": "https://avatars2.githubusercontent.com/u/5751682?v=4", 
      "gravatar_id": "", 
      "site_admin": false, 
      "login": "brendandburns", 
      "type": "User", 
      "id": 5751682
    }, 
    "id": 57666542
  }, 
  "pull_request": {
    "merge_commit_sha": "5267d37fa40fc7905e1eb171563346c71fb16599", 
    "number": 51025, 
    "assignee": {
      "html_url": "https://github.com/brendandburns", 
      "avatar_url": "https://avatars2.githubusercontent.com/u/5751682?v=4", 
      "gravatar_id": "", 
      "site_admin": false, 
      "login": "brendandburns", 
      "type": "User", 
      "id": 5751682
    }, 
    "closed_at": null, 
    "requested_reviewers": [], 
    "id": 136757895, 
    "title": "Update defaults.go", 
    "merged_at": null, 
    "state": "open", 
    "_links": {
      "review_comment": {
        "href": "https://api.github.com/repos/kubernetes/kubernetes/pulls/comments{/number}"
      }, 
      "commits": {
        "href": "https://api.github.com/repos/kubernetes/kubernetes/pulls/51025/commits"
      }, 
      "self": {
        "href": "https://api.github.com/repos/kubernetes/kubernetes/pulls/51025"
      }, 
      "review_comments": {
        "href": "https://api.github.com/repos/kubernetes/kubernetes/pulls/51025/comments"
      }, 
      "html": {
        "href": "https://github.com/kubernetes/kubernetes/pull/51025"
      }, 
      "comments": {
        "href": "https://api.github.com/repos/kubernetes/kubernetes/issues/51025/comments"
      }, 
      "issue": {
        "href": "https://api.github.com/repos/kubernetes/kubernetes/issues/51025"
      }, 
      "statuses": {
        "href": "https://api.github.com/repos/kubernetes/kubernetes/statuses/3257d8d28ba6e4abca8153583869fc9749e809e7"
      }
    }, 
    "diff_url": "https://github.com/kubernetes/kubernetes/pull/51025.diff", 
    "body": "\r\n**What this PR does / why we need it**:\r\nAdd explain about TaintTolerationPriority function.\r\n\r\n\r\n**Which issue this PR fixes** *(optional, in `fixes #<issue number>(, fixes #<issue_number>, ...)` format, will close that issue when PR gets merged)*: fixes #\r\n\r\n**Special notes for your reviewer**:\r\n\r\n**Release note**:\r\n<!--  Steps to write your release note:\r\n1. Use the release-note-* labels to set the release note state (if you have access)\r\n2. Enter your extended release note in the below block; leaving it blank means using the PR title as the release note. If no release note is required, just write `NONE`.\r\n-->\r\n```release-note\r\nNone.\r\n```\r\n", 
    "head": {
      "repo": {
        "stargazers_count": 0, 
        "mirror_url": null, 
        "updated_at": "2017-08-21T12:30:11Z", 
        "private": false, 
        "has_wiki": true, 
        "full_name": "stewart-yu/kubernetes", 
        "owner": {
          "html_url": "https://github.com/stewart-yu", 
          "avatar_url": "https://avatars2.githubusercontent.com/u/30410021?v=4", 
          "gravatar_id": "", 
          "site_admin": false, 
          "login": "stewart-yu", 
          "type": "User", 
          "id": 30410021
        }, 
        "id": 100950156, 
        "description": "Production-Grade Container Scheduling and Management", 
        "has_pages": false, 
        "open_issues_count": 0, 
        "has_projects": true, 
        "clone_url": "https://github.com/stewart-yu/kubernetes.git", 
        "watchers_count": 0, 
        "size": 460704, 
        "homepage": "http://kubernetes.io", 
        "fork": true, 
        "html_url": "https://github.com/stewart-yu/kubernetes", 
        "forks": 0, 
        "open_issues": 0, 
        "git_url": "git://github.com/stewart-yu/kubernetes.git", 
        "svn_url": "https://github.com/stewart-yu/kubernetes", 
        "has_issues": false, 
        "ssh_url": "git@github.com:stewart-yu/kubernetes.git", 
        "has_downloads": true, 
        "watchers": 0, 
        "name": "kubernetes", 
        "language": "Go", 
        "created_at": "2017-08-21T12:29:29Z", 
        "pushed_at": "2017-08-21T13:14:51Z", 
        "forks_count": 0, 
        "default_branch": "master"
      }, 
      "sha": "3257d8d28ba6e4abca8153583869fc9749e809e7", 
      "ref": "master", 
      "user": {
        "html_url": "https://github.com/stewart-yu", 
        "avatar_url": "https://avatars2.githubusercontent.com/u/30410021?v=4", 
        "gravatar_id": "", 
        "site_admin": false, 
        "login": "stewart-yu", 
        "type": "User", 
        "id": 30410021
      }, 
      "label": "stewart-yu:master"
    }, 
    "html_url": "https://github.com/kubernetes/kubernetes/pull/51025", 
    "updated_at": "2017-08-22T04:43:19Z", 
    "base": {
      "repo": {
        "stargazers_count": 26148, 
        "mirror_url": null, 
        "updated_at": "2017-08-22T03:50:19Z", 
        "private": false, 
        "has_wiki": true, 
        "full_name": "kubernetes/kubernetes", 
        "owner": {
          "html_url": "https://github.com/kubernetes", 
          "avatar_url": "https://avatars2.githubusercontent.com/u/13629408?v=4", 
          "gravatar_id": "", 
          "site_admin": false, 
          "login": "kubernetes", 
          "type": "Organization", 
          "id": 13629408
        }, 
        "id": 20580498, 
        "description": "Production-Grade Container Scheduling and Management", 
        "has_pages": false, 
        "open_issues_count": 5327, 
        "has_projects": true, 
        "clone_url": "https://github.com/kubernetes/kubernetes.git", 
        "watchers_count": 26148, 
        "size": 677615, 
        "homepage": "http://kubernetes.io", 
        "fork": false, 
        "html_url": "https://github.com/kubernetes/kubernetes", 
        "forks": 9313, 
        "open_issues": 5327, 
        "git_url": "git://github.com/kubernetes/kubernetes.git", 
        "svn_url": "https://github.com/kubernetes/kubernetes", 
        "has_issues": true, 
        "ssh_url": "git@github.com:kubernetes/kubernetes.git", 
        "has_downloads": true, 
        "watchers": 26148, 
        "name": "kubernetes", 
        "language": "Go", 
        "created_at": "2014-06-06T22:56:04Z", 
        "pushed_at": "2017-08-22T04:27:34Z", 
        "forks_count": 9313, 
        "default_branch": "master"
      }, 
      "sha": "f4afdecef85e83e7b83fc8a6d63a220c9a10acc0", 
      "ref": "master", 
      "user": {
        "html_url": "https://github.com/kubernetes", 
        "avatar_url": "https://avatars2.githubusercontent.com/u/13629408?v=4", 
        "gravatar_id": "", 
        "site_admin": false, 
        "login": "kubernetes", 
        "type": "Organization", 
        "id": 13629408
      }, 
      "label": "kubernetes:master"
    }, 
    "user": {
      "html_url": "https://github.com/stewart-yu", 
      "avatar_url": "https://avatars2.githubusercontent.com/u/30410021?v=4", 
      "gravatar_id": "", 
      "site_admin": false, 
      "login": "stewart-yu", 
      "type": "User", 
      "id": 30410021
    }, 
    "milestone": null, 
    "locked": false, 
    "created_at": "2017-08-21T13:16:44Z", 
    "assignees": [
      {
        "html_url": "https://github.com/thockin", 
        "avatar_url": "https://avatars0.githubusercontent.com/u/5595220?v=4", 
        "gravatar_id": "", 
        "site_admin": false, 
        "login": "thockin", 
        "type": "User", 
        "id": 5595220
      }, 
      {
        "html_url": "https://github.com/brendandburns", 
        "avatar_url": "https://avatars2.githubusercontent.com/u/5751682?v=4", 
        "gravatar_id": "", 
        "site_admin": false, 
        "login": "brendandburns", 
        "type": "User", 
        "id": 5751682
      }
    ], 
    "patch_url": "https://github.com/kubernetes/kubernetes/pull/51025.patch"
  }, 
  "action": "submitted", 
  "organization": {
    "description": "Kubernetes", 
    "avatar_url": "https://avatars2.githubusercontent.com/u/13629408?v=4", 
    "login": "kubernetes", 
    "id": 13629408
  }
}
